{
  "region_id": 10000067,
  "faction_id": 500003,
  "center": {
    "x": 134.0,
    "y": 315.0
  },
  "relations": [
    "10000002",
    "10000032",
    "10000037",
    "10000042",
    "10000052",
    "10000054",
    "10000064",
    "10000065",
    "10000068"
  ],
  "systems": {
    "30005233": {
      "x": 0.0,
      "y": 54.0
    },
    "30005232": {
      "x": 0.0,
      "y": 100.0
    },
    "30005235": {
      "x": 0.0,
      "y": 170.0
    },
    "30005267": {
      "x": 0.0,
      "y": 235.0
    },
    "30005268": {
      "x": 0.0,
      "y": 365.0
    },
    "30005258": {
      "x": 0.0,
      "y": 470.0
    },
    "30005257": {
      "x": 0.0,
      "y": 730.0
    },
    "30005271": {
      "x": 40.0,
      "y": 415.0
    },
    "30005275": {
      "x": 44.0,
      "y": 527.0
    },
    "30005259": {
      "x": 47.0,
      "y": 695.0
    },
    "30005269": {
      "x": 50.0,
      "y": 200.0
    },
    "30005231": {
      "x": 57.0,
      "y": 76.0
    },
    "30005278": {
      "x": 64.0,
      "y": 613.0
    },
    "30005270": {
      "x": 70.0,
      "y": 370.0
    },
    "30005234": {
      "x": 74.0,
      "y": 124.0
    },
    "30005276": {
      "x": 101.0,
      "y": 585.0
    },
    "30005272": {
      "x": 105.0,
      "y": 325.0
    },
    "30005273": {
      "x": 105.0,
      "y": 415.0
    },
    "30005230": {
      "x": 109.0,
      "y": 34.0
    },
    "30005277": {
      "x": 126.0,
      "y": 557.0
    },
    "30005279": {
      "x": 128.0,
      "y": 619.0
    },
    "30005280": {
      "x": 134.0,
      "y": 658.0
    },
    "30005274": {
      "x": 140.0,
      "y": 370.0
    },
    "30005260": {
      "x": 178.0,
      "y": 510.0
    },
    "30005229": {
      "x": 187.0,
      "y": 26.0
    },
    "30005255": {
      "x": 205.0,
      "y": 730.0
    },
    "30005256": {
      "x": 234.0,
      "y": 529.0
    },
    "30005253": {
      "x": 245.0,
      "y": 399.0
    },
    "30005254": {
      "x": 248.0,
      "y": 440.0
    },
    "30005291": {
      "x": 275.0,
      "y": 225.0
    },
    "30005281": {
      "x": 290.0,
      "y": 585.0
    },
    "30005204": {
      "x": 305.0,
      "y": 74.0
    },
    "30005206": {
      "x": 305.0,
      "y": 105.0
    },
    "30005282": {
      "x": 305.0,
      "y": 625.0
    },
    "30005250": {
      "x": 307.0,
      "y": 420.0
    },
    "30005251": {
      "x": 307.0,
      "y": 456.0
    },
    "30005292": {
      "x": 308.0,
      "y": 286.0
    },
    "30005294": {
      "x": 318.0,
      "y": 195.0
    },
    "30005290": {
      "x": 330.0,
      "y": 245.0
    },
    "30005266": {
      "x": 335.0,
      "y": 540.0
    },
    "30005252": {
      "x": 336.0,
      "y": 486.0
    },
    "30005285": {
      "x": 365.0,
      "y": 685.0
    },
    "30005293": {
      "x": 369.0,
      "y": 313.0
    },
    "30005283": {
      "x": 375.0,
      "y": 645.0
    },
    "30005249": {
      "x": 376.0,
      "y": 445.0
    },
    "30005287": {
      "x": 385.0,
      "y": 605.0
    },
    "30005289": {
      "x": 389.0,
      "y": 224.0
    },
    "30005203": {
      "x": 390.0,
      "y": 73.0
    },
    "30005201": {
      "x": 391.0,
      "y": 105.0
    },
    "30005288": {
      "x": 394.0,
      "y": 190.0
    },
    "30005264": {
      "x": 400.0,
      "y": 525.0
    },
    "30005223": {
      "x": 428.0,
      "y": 285.0
    },
    "30005265": {
      "x": 450.0,
      "y": 560.0
    },
    "30005284": {
      "x": 450.0,
      "y": 655.0
    },
    "30005222": {
      "x": 461.0,
      "y": 253.0
    },
    "30005199": {
      "x": 466.0,
      "y": 107.0
    },
    "30005205": {
      "x": 467.0,
      "y": 190.0
    },
    "30005221": {
      "x": 467.0,
      "y": 225.0
    },
    "30005200": {
      "x": 474.0,
      "y": 148.0
    },
    "30005262": {
      "x": 485.0,
      "y": 525.0
    },
    "30005228": {
      "x": 488.0,
      "y": 289.0
    },
    "30005202": {
      "x": 519.0,
      "y": 57.0
    },
    "30005286": {
      "x": 525.0,
      "y": 665.0
    },
    "30005263": {
      "x": 535.0,
      "y": 555.0
    },
    "30005242": {
      "x": 545.0,
      "y": 730.0
    },
    "30005198": {
      "x": 548.0,
      "y": 100.0
    },
    "30005224": {
      "x": 549.0,
      "y": 271.0
    },
    "30005225": {
      "x": 550.0,
      "y": 304.0
    },
    "30005195": {
      "x": 563.0,
      "y": 182.0
    },
    "30005226": {
      "x": 602.0,
      "y": 329.0
    },
    "30005214": {
      "x": 604.0,
      "y": 0.0
    },
    "30005240": {
      "x": 610.0,
      "y": 680.0
    },
    "30005261": {
      "x": 615.0,
      "y": 535.0
    },
    "30005208": {
      "x": 637.0,
      "y": 269.0
    },
    "30005194": {
      "x": 638.0,
      "y": 182.0
    },
    "30005246": {
      "x": 639.0,
      "y": 479.0
    },
    "30005239": {
      "x": 640.0,
      "y": 585.0
    },
    "30005227": {
      "x": 663.0,
      "y": 335.0
    },
    "30005243": {
      "x": 675.0,
      "y": 407.0
    },
    "30005193": {
      "x": 680.0,
      "y": 139.0
    },
    "30005207": {
      "x": 685.0,
      "y": 242.0
    },
    "30005237": {
      "x": 685.0,
      "y": 635.0
    },
    "30005197": {
      "x": 699.0,
      "y": 203.0
    },
    "30005236": {
      "x": 710.0,
      "y": 685.0
    },
    "30005238": {
      "x": 710.0,
      "y": 730.0
    },
    "30005244": {
      "x": 711.0,
      "y": 448.0
    },
    "30005241": {
      "x": 716.0,
      "y": 585.0
    },
    "30005192": {
      "x": 719.0,
      "y": 111.0
    },
    "30005196": {
      "x": 750.0,
      "y": 149.0
    },
    "30005215": {
      "x": 767.0,
      "y": 1.0
    },
    "30004120": {
      "x": 770.0,
      "y": 557.0
    },
    "30005245": {
      "x": 818.0,
      "y": 409.0
    },
    "30004118": {
      "x": 825.0,
      "y": 526.0
    },
    "30005247": {
      "x": 828.0,
      "y": 450.0
    },
    "30005216": {
      "x": 840.0,
      "y": 0.0
    },
    "30005217": {
      "x": 856.0,
      "y": 33.0
    },
    "30005220": {
      "x": 861.0,
      "y": 169.0
    },
    "30005218": {
      "x": 874.0,
      "y": 80.0
    },
    "30005219": {
      "x": 875.0,
      "y": 129.0
    },
    "30005248": {
      "x": 889.0,
      "y": 428.0
    },
    "30005209": {
      "x": 894.0,
      "y": 252.0
    },
    "30005210": {
      "x": 949.0,
      "y": 148.0
    },
    "30005211": {
      "x": 953.0,
      "y": 100.0
    },
    "30005212": {
      "x": 958.0,
      "y": 189.0
    },
    "30005213": {
      "x": 960.0,
      "y": 252.0
    },
    "30004230": {
      "x": 205.0,
      "y": 345.0
    },
    "30004987": {
      "x": 245.0,
      "y": 89.0
    },
    "30004994": {
      "x": 263.0,
      "y": 128.0
    },
    "30005301": {
      "x": 305.0,
      "y": 42.0
    },
    "30005024": {
      "x": 319.0,
      "y": 0.0
    },
    "30005331": {
      "x": 384.0,
      "y": 0.0
    },
    "30003052": {
      "x": 390.0,
      "y": 135.0
    },
    "30003055": {
      "x": 390.0,
      "y": 161.0
    },
    "30002661": {
      "x": 443.0,
      "y": 0.0
    },
    "30005303": {
      "x": 445.0,
      "y": 54.0
    },
    "30005001": {
      "x": 524.0,
      "y": 7.0
    },
    "30004969": {
      "x": 550.0,
      "y": 133.0
    },
    "30005015": {
      "x": 589.0,
      "y": 47.0
    },
    "30004970": {
      "x": 626.0,
      "y": 117.0
    },
    "30003452": {
      "x": 641.0,
      "y": 76.0
    },
    "30004104": {
      "x": 651.0,
      "y": 367.0
    },
    "30004122": {
      "x": 682.0,
      "y": 304.0
    },
    "30004083": {
      "x": 737.0,
      "y": 59.0
    },
    "30005031": {
      "x": 780.0,
      "y": 685.0
    },
    "30005077": {
      "x": 780.0,
      "y": 730.0
    },
    "30004115": {
      "x": 782.0,
      "y": 87.0
    },
    "30000134": {
      "x": 783.0,
      "y": 182.0
    },
    "30004117": {
      "x": 878.0,
      "y": 500.0
    },
    "30004116": {
      "x": 923.0,
      "y": 465.0
    }
  },
  "jumps": {
    "30004118": [
      "30004117",
      "30004120"
    ],
    "30004117": [
      "30004118",
      "30004116"
    ],
    "30004120": [
      "30004118",
      "30005241"
    ],
    "30005241": [
      "30004120",
      "30005239"
    ],
    "30005192": [
      "30004083",
      "30004115",
      "30005193",
      "30005196"
    ],
    "30004083": [
      "30005192"
    ],
    "30004115": [
      "30005192"
    ],
    "30005193": [
      "30005192",
      "30005194",
      "30005196"
    ],
    "30005196": [
      "30005192",
      "30005193",
      "30000134"
    ],
    "30005194": [
      "30005193",
      "30005195",
      "30005197"
    ],
    "30005195": [
      "30005194",
      "30005205"
    ],
    "30005197": [
      "30005194",
      "30005207"
    ],
    "30005205": [
      "30005195",
      "30005200",
      "30005221",
      "30005288"
    ],
    "30000134": [
      "30005196"
    ],
    "30005207": [
      "30005197",
      "30005208"
    ],
    "30005198": [
      "30003452",
      "30004969",
      "30004970",
      "30005015",
      "30005199"
    ],
    "30003452": [
      "30005198"
    ],
    "30004969": [
      "30005198",
      "30004970"
    ],
    "30004970": [
      "30005198",
      "30004969"
    ],
    "30005015": [
      "30005198"
    ],
    "30005199": [
      "30005198",
      "30005200",
      "30005201",
      "30005303"
    ],
    "30005200": [
      "30005199",
      "30005205"
    ],
    "30005201": [
      "30005199",
      "30003052",
      "30005202",
      "30005203",
      "30005206"
    ],
    "30005303": [
      "30005199",
      "30005301"
    ],
    "30003052": [
      "30005201",
      "30003055"
    ],
    "30005202": [
      "30005201",
      "30005001",
      "30005214"
    ],
    "30005203": [
      "30005201",
      "30002661",
      "30005024",
      "30005204",
      "30005331"
    ],
    "30005206": [
      "30005201",
      "30005204",
      "30004987",
      "30004994"
    ],
    "30005001": [
      "30005202"
    ],
    "30005214": [
      "30005202",
      "30005215"
    ],
    "30002661": [
      "30005203"
    ],
    "30005024": [
      "30005203"
    ],
    "30005204": [
      "30005203",
      "30005206",
      "30005301"
    ],
    "30005331": [
      "30005203"
    ],
    "30005301": [
      "30005204",
      "30005229",
      "30005303"
    ],
    "30005221": [
      "30005205",
      "30005222",
      "30005289"
    ],
    "30005288": [
      "30005205",
      "30003055",
      "30005289"
    ],
    "30004987": [
      "30005206"
    ],
    "30004994": [
      "30005206"
    ],
    "30005208": [
      "30005207",
      "30005209",
      "30005224"
    ],
    "30005209": [
      "30005208",
      "30005210",
      "30005244"
    ],
    "30005224": [
      "30005208",
      "30005222",
      "30005225",
      "30005228"
    ],
    "30005210": [
      "30005209",
      "30005211",
      "30005212",
      "30005219"
    ],
    "30005244": [
      "30005209",
      "30005243",
      "30005245",
      "30005246",
      "30005247"
    ],
    "30005211": [
      "30005210",
      "30005218"
    ],
    "30005212": [
      "30005210",
      "30005213"
    ],
    "30005219": [
      "30005210",
      "30005218",
      "30005220"
    ],
    "30005218": [
      "30005211",
      "30005217",
      "30005219"
    ],
    "30005213": [
      "30005212"
    ],
    "30005215": [
      "30005214",
      "30005216",
      "30005217"
    ],
    "30005216": [
      "30005215",
      "30005217"
    ],
    "30005217": [
      "30005215",
      "30005216",
      "30005218"
    ],
    "30005220": [
      "30005219",
      "30005243"
    ],
    "30005243": [
      "30005220",
      "30005244",
      "30005293"
    ],
    "30005222": [
      "30005221",
      "30005223",
      "30005224"
    ],
    "30005289": [
      "30005221",
      "30005288",
      "30005290",
      "30005294"
    ],
    "30005223": [
      "30005222",
      "30005292"
    ],
    "30005292": [
      "30005223",
      "30005290",
      "30005293"
    ],
    "30005225": [
      "30005224",
      "30005226",
      "30005228"
    ],
    "30005228": [
      "30005224",
      "30005225"
    ],
    "30005226": [
      "30005225",
      "30005227"
    ],
    "30005227": [
      "30005226",
      "30004104",
      "30004122"
    ],
    "30004104": [
      "30005227"
    ],
    "30004122": [
      "30005227"
    ],
    "30005230": [
      "30005229",
      "30005231"
    ],
    "30005229": [
      "30005230",
      "30005301"
    ],
    "30005231": [
      "30005230",
      "30005232",
      "30005233",
      "30005234"
    ],
    "30005232": [
      "30005231",
      "30005233",
      "30005235"
    ],
    "30005233": [
      "30005231",
      "30005232"
    ],
    "30005234": [
      "30005231",
      "30005291"
    ],
    "30005235": [
      "30005232",
      "30005267"
    ],
    "30005291": [
      "30005234",
      "30005290",
      "30005294"
    ],
    "30005267": [
      "30005235",
      "30005268",
      "30005269"
    ],
    "30005236": [
      "30005031",
      "30005237",
      "30005238"
    ],
    "30005031": [
      "30005236"
    ],
    "30005237": [
      "30005236",
      "30005239",
      "30005240"
    ],
    "30005238": [
      "30005236",
      "30005077"
    ],
    "30005239": [
      "30005237",
      "30005240",
      "30005241",
      "30005261"
    ],
    "30005240": [
      "30005237",
      "30005239",
      "30005242"
    ],
    "30005077": [
      "30005238"
    ],
    "30005261": [
      "30005239",
      "30005246",
      "30005262",
      "30005263"
    ],
    "30005242": [
      "30005240",
      "30005255"
    ],
    "30005255": [
      "30005242",
      "30005256",
      "30005257"
    ],
    "30005293": [
      "30005243",
      "30005290",
      "30005292"
    ],
    "30005245": [
      "30005244",
      "30005247",
      "30005248"
    ],
    "30005246": [
      "30005244",
      "30005249",
      "30005261"
    ],
    "30005247": [
      "30005244",
      "30005245",
      "30005248"
    ],
    "30005248": [
      "30005245",
      "30005247",
      "30004116"
    ],
    "30005249": [
      "30005246",
      "30005250",
      "30005251",
      "30005252"
    ],
    "30004116": [
      "30005248",
      "30004117"
    ],
    "30005250": [
      "30005249",
      "30005253",
      "30005254"
    ],
    "30005251": [
      "30005249",
      "30005256"
    ],
    "30005252": [
      "30005249",
      "30005256"
    ],
    "30005253": [
      "30005250"
    ],
    "30005254": [
      "30005250",
      "30005256"
    ],
    "30005256": [
      "30005251",
      "30005252",
      "30005254",
      "30005255",
      "30005260"
    ],
    "30005257": [
      "30005255",
      "30005258",
      "30005259",
      "30005275"
    ],
    "30005260": [
      "30005256"
    ],
    "30005258": [
      "30005257",
      "30005268"
    ],
    "30005259": [
      "30005257"
    ],
    "30005275": [
      "30005257",
      "30005273",
      "30005276"
    ],
    "30005268": [
      "30005258",
      "30005267",
      "30005270",
      "30005271"
    ],
    "30005262": [
      "30005261",
      "30005263",
      "30005264",
      "30005265"
    ],
    "30005263": [
      "30005261",
      "30005262"
    ],
    "30005264": [
      "30005262",
      "30005265",
      "30005266"
    ],
    "30005265": [
      "30005262",
      "30005264"
    ],
    "30005266": [
      "30005264",
      "30005281"
    ],
    "30005281": [
      "30005266",
      "30005282"
    ],
    "30005269": [
      "30005267"
    ],
    "30005270": [
      "30005268",
      "30005271",
      "30005272",
      "30005273"
    ],
    "30005271": [
      "30005268",
      "30005270",
      "30005273"
    ],
    "30005272": [
      "30005270",
      "30005274"
    ],
    "30005273": [
      "30005270",
      "30005271",
      "30005274",
      "30005275"
    ],
    "30005274": [
      "30005272",
      "30005273",
      "30004230"
    ],
    "30004230": [
      "30005274"
    ],
    "30005276": [
      "30005275",
      "30005277",
      "30005278",
      "30005279"
    ],
    "30005277": [
      "30005276"
    ],
    "30005278": [
      "30005276"
    ],
    "30005279": [
      "30005276",
      "30005280"
    ],
    "30005280": [
      "30005279"
    ],
    "30005282": [
      "30005281",
      "30005283"
    ],
    "30005283": [
      "30005282",
      "30005284",
      "30005285",
      "30005287"
    ],
    "30005284": [
      "30005283",
      "30005286"
    ],
    "30005285": [
      "30005283"
    ],
    "30005287": [
      "30005283"
    ],
    "30005286": [
      "30005284"
    ],
    "30003055": [
      "30005288",
      "30003052"
    ],
    "30005290": [
      "30005289",
      "30005291",
      "30005292",
      "30005293"
    ],
    "30005294": [
      "30005289",
      "30005291"
    ]
  }
}