{
  "region_id": 10000008,
  "faction_id": 0,
  "center": {
    "x": 542.0,
    "y": 368.0
  },
  "relations": [
    "10000006",
    "10000009",
    "10000011",
    "10000012"
  ],
  "systems": {
    "30000675": {
      "x": 0.0,
      "y": 85.0
    },
    "30000728": {
      "x": 0.0,
      "y": 175.0
    },
    "30000723": {
      "x": 0.0,
      "y": 270.0
    },
    "30000724": {
      "x": 0.0,
      "y": 340.0
    },
    "30000687": {
      "x": 25.0,
      "y": 506.0
    },
    "30000690": {
      "x": 25.0,
      "y": 546.0
    },
    "30000688": {
      "x": 25.0,
      "y": 590.0
    },
    "30000686": {
      "x": 25.0,
      "y": 635.0
    },
    "30000685": {
      "x": 25.0,
      "y": 675.0
    },
    "30000689": {
      "x": 25.0,
      "y": 715.0
    },
    "30000727": {
      "x": 45.0,
      "y": 225.0
    },
    "30000722": {
      "x": 65.0,
      "y": 315.0
    },
    "30000676": {
      "x": 80.0,
      "y": 25.0
    },
    "30000672": {
      "x": 80.0,
      "y": 85.0
    },
    "30001021": {
      "x": 120.0,
      "y": 630.0
    },
    "30000702": {
      "x": 125.0,
      "y": 175.0
    },
    "30000700": {
      "x": 125.0,
      "y": 235.0
    },
    "30000677": {
      "x": 150.0,
      "y": 25.0
    },
    "30000673": {
      "x": 150.0,
      "y": 85.0
    },
    "30001019": {
      "x": 160.0,
      "y": 430.0
    },
    "30000721": {
      "x": 175.0,
      "y": 315.0
    },
    "30000693": {
      "x": 180.0,
      "y": 520.0
    },
    "30000696": {
      "x": 190.0,
      "y": 485.0
    },
    "30000692": {
      "x": 195.0,
      "y": 550.0
    },
    "30000674": {
      "x": 210.0,
      "y": 55.0
    },
    "30000701": {
      "x": 215.0,
      "y": 170.0
    },
    "30000699": {
      "x": 215.0,
      "y": 215.0
    },
    "30000695": {
      "x": 240.0,
      "y": 575.0
    },
    "30000667": {
      "x": 255.0,
      "y": 105.0
    },
    "30000665": {
      "x": 255.0,
      "y": 470.0
    },
    "30000725": {
      "x": 275.0,
      "y": 290.0
    },
    "30000729": {
      "x": 275.0,
      "y": 340.0
    },
    "30000660": {
      "x": 285.0,
      "y": 525.0
    },
    "30000694": {
      "x": 285.0,
      "y": 605.0
    },
    "30000697": {
      "x": 305.0,
      "y": 230.0
    },
    "30000698": {
      "x": 315.0,
      "y": 185.0
    },
    "30000656": {
      "x": 320.0,
      "y": 430.0
    },
    "30000691": {
      "x": 323.0,
      "y": 576.0
    },
    "30000726": {
      "x": 330.0,
      "y": 315.0
    },
    "30000661": {
      "x": 330.0,
      "y": 485.0
    },
    "30000666": {
      "x": 355.0,
      "y": 105.0
    },
    "30000659": {
      "x": 370.0,
      "y": 525.0
    },
    "30001029": {
      "x": 395.0,
      "y": 610.0
    },
    "30000668": {
      "x": 415.0,
      "y": 120.0
    },
    "30000658": {
      "x": 430.0,
      "y": 465.0
    },
    "30001031": {
      "x": 430.0,
      "y": 665.0
    },
    "30000657": {
      "x": 435.0,
      "y": 555.0
    },
    "30000671": {
      "x": 450.0,
      "y": 330.0
    },
    "30000655": {
      "x": 480.0,
      "y": 525.0
    },
    "30000669": {
      "x": 485.0,
      "y": 155.0
    },
    "30000670": {
      "x": 550.0,
      "y": 180.0
    },
    "30000714": {
      "x": 560.0,
      "y": 35.0
    },
    "30000732": {
      "x": 585.0,
      "y": 320.0
    },
    "30000730": {
      "x": 600.0,
      "y": 380.0
    },
    "30000710": {
      "x": 615.0,
      "y": 105.0
    },
    "30000684": {
      "x": 620.0,
      "y": 150.0
    },
    "30000662": {
      "x": 620.0,
      "y": 565.0
    },
    "30000678": {
      "x": 625.0,
      "y": 190.0
    },
    "30000733": {
      "x": 625.0,
      "y": 255.0
    },
    "30000709": {
      "x": 640.0,
      "y": 55.0
    },
    "30000711": {
      "x": 665.0,
      "y": 10.0
    },
    "30000731": {
      "x": 670.0,
      "y": 405.0
    },
    "30000664": {
      "x": 685.0,
      "y": 565.0
    },
    "30000734": {
      "x": 695.0,
      "y": 335.0
    },
    "30000712": {
      "x": 700.0,
      "y": 45.0
    },
    "30000735": {
      "x": 700.0,
      "y": 295.0
    },
    "30000682": {
      "x": 720.0,
      "y": 185.0
    },
    "30000663": {
      "x": 755.0,
      "y": 565.0
    },
    "30000713": {
      "x": 760.0,
      "y": 85.0
    },
    "30000683": {
      "x": 800.0,
      "y": 305.0
    },
    "30000679": {
      "x": 810.0,
      "y": 380.0
    },
    "30000708": {
      "x": 820.0,
      "y": 5.0
    },
    "30000707": {
      "x": 820.0,
      "y": 35.0
    },
    "30000705": {
      "x": 820.0,
      "y": 65.0
    },
    "30000704": {
      "x": 865.0,
      "y": 110.0
    },
    "30000680": {
      "x": 885.0,
      "y": 175.0
    },
    "30000681": {
      "x": 885.0,
      "y": 224.0
    },
    "30000717": {
      "x": 885.0,
      "y": 340.0
    },
    "30000715": {
      "x": 885.0,
      "y": 375.0
    },
    "30000718": {
      "x": 885.0,
      "y": 415.0
    },
    "30000716": {
      "x": 885.0,
      "y": 450.0
    },
    "30000706": {
      "x": 905.0,
      "y": 5.0
    },
    "30000703": {
      "x": 905.0,
      "y": 65.0
    },
    "30000719": {
      "x": 955.0,
      "y": 375.0
    },
    "30000720": {
      "x": 955.0,
      "y": 415.0
    },
    "30001016": {
      "x": 95.0,
      "y": 485.0
    },
    "30001018": {
      "x": 95.0,
      "y": 550.0
    },
    "30001017": {
      "x": 105.0,
      "y": 395.0
    },
    "30001011": {
      "x": 180.0,
      "y": 380.0
    },
    "30001032": {
      "x": 265.0,
      "y": 690.0
    },
    "30000926": {
      "x": 300.0,
      "y": 25.0
    },
    "30000939": {
      "x": 405.0,
      "y": 25.0
    },
    "30001001": {
      "x": 470.0,
      "y": 610.0
    },
    "30001033": {
      "x": 500.0,
      "y": 715.0
    },
    "30000570": {
      "x": 635.0,
      "y": 450.0
    },
    "30000568": {
      "x": 660.0,
      "y": 505.0
    },
    "30000789": {
      "x": 760.0,
      "y": 120.0
    },
    "30000583": {
      "x": 775.0,
      "y": 520.0
    },
    "30000563": {
      "x": 790.0,
      "y": 425.0
    },
    "30000588": {
      "x": 885.0,
      "y": 485.0
    },
    "30000792": {
      "x": 960.0,
      "y": 145.0
    },
    "30000554": {
      "x": 960.0,
      "y": 201.0
    },
    "30000774": {
      "x": 960.0,
      "y": 480.0
    },
    "30000787": {
      "x": 965.0,
      "y": 5.0
    },
    "30000978": {
      "x": 965.0,
      "y": 65.0
    }
  },
  "jumps": {
    "30000657": [
      "30000655",
      "30000659",
      "30001001",
      "30001029"
    ],
    "30000655": [
      "30000657",
      "30000658",
      "30000662",
      "30000671"
    ],
    "30000658": [
      "30000655",
      "30000656",
      "30000659",
      "30000671",
      "30000721"
    ],
    "30000662": [
      "30000655",
      "30000664"
    ],
    "30000671": [
      "30000655",
      "30000658",
      "30000669",
      "30000697"
    ],
    "30000656": [
      "30000658",
      "30000661",
      "30000665",
      "30000668",
      "30001019"
    ],
    "30000661": [
      "30000656"
    ],
    "30000665": [
      "30000656",
      "30000660"
    ],
    "30000668": [
      "30000656",
      "30000666",
      "30000669"
    ],
    "30001019": [
      "30000656",
      "30001011",
      "30001016",
      "30001017"
    ],
    "30000659": [
      "30000657",
      "30000658",
      "30000660",
      "30000691"
    ],
    "30001001": [
      "30000657",
      "30001031"
    ],
    "30001029": [
      "30000657",
      "30001031"
    ],
    "30000721": [
      "30000658",
      "30000697",
      "30000699",
      "30000722",
      "30000725",
      "30000729"
    ],
    "30000660": [
      "30000659",
      "30000665"
    ],
    "30000691": [
      "30000659",
      "30000694",
      "30000695"
    ],
    "30000664": [
      "30000662",
      "30000663",
      "30000568"
    ],
    "30000663": [
      "30000583",
      "30000664"
    ],
    "30000583": [
      "30000663"
    ],
    "30000568": [
      "30000664",
      "30000570"
    ],
    "30000667": [
      "30000666",
      "30000673"
    ],
    "30000666": [
      "30000667",
      "30000668",
      "30000926",
      "30000939"
    ],
    "30000926": [
      "30000666"
    ],
    "30000939": [
      "30000666"
    ],
    "30000673": [
      "30000667",
      "30000672",
      "30000674",
      "30000677"
    ],
    "30000669": [
      "30000668",
      "30000670",
      "30000671"
    ],
    "30000670": [
      "30000669",
      "30000678",
      "30000732"
    ],
    "30000678": [
      "30000670",
      "30000682",
      "30000683",
      "30000684"
    ],
    "30000732": [
      "30000670",
      "30000730",
      "30000733",
      "30000734"
    ],
    "30000697": [
      "30000671",
      "30000698",
      "30000699",
      "30000701",
      "30000721"
    ],
    "30000672": [
      "30000673",
      "30000675",
      "30000676"
    ],
    "30000675": [
      "30000672"
    ],
    "30000676": [
      "30000672",
      "30000677"
    ],
    "30000674": [
      "30000673",
      "30000677"
    ],
    "30000677": [
      "30000673",
      "30000674",
      "30000676"
    ],
    "30000682": [
      "30000678",
      "30000680"
    ],
    "30000683": [
      "30000678",
      "30000679"
    ],
    "30000684": [
      "30000678",
      "30000710"
    ],
    "30000679": [
      "30000563",
      "30000683",
      "30000730"
    ],
    "30000563": [
      "30000679"
    ],
    "30000730": [
      "30000679",
      "30000570",
      "30000731",
      "30000732",
      "30000734"
    ],
    "30000680": [
      "30000554",
      "30000681",
      "30000682",
      "30000704",
      "30000792"
    ],
    "30000554": [
      "30000680",
      "30000681"
    ],
    "30000681": [
      "30000680",
      "30000554",
      "30000717"
    ],
    "30000704": [
      "30000680",
      "30000703",
      "30000705"
    ],
    "30000792": [
      "30000680"
    ],
    "30000717": [
      "30000681",
      "30000715"
    ],
    "30000710": [
      "30000684",
      "30000709",
      "30000714"
    ],
    "30000686": [
      "30000685",
      "30000688"
    ],
    "30000685": [
      "30000686",
      "30000689"
    ],
    "30000689": [
      "30000685"
    ],
    "30000688": [
      "30000686",
      "30000690",
      "30001021"
    ],
    "30000690": [
      "30000687",
      "30000688"
    ],
    "30000687": [
      "30000690",
      "30000722"
    ],
    "30000722": [
      "30000687",
      "30000700",
      "30000721",
      "30000723",
      "30000724",
      "30000727"
    ],
    "30001021": [
      "30000688",
      "30001018",
      "30001032"
    ],
    "30000694": [
      "30000691",
      "30000695"
    ],
    "30000695": [
      "30000691",
      "30000692",
      "30000694"
    ],
    "30000693": [
      "30000692",
      "30000696"
    ],
    "30000692": [
      "30000693",
      "30000695"
    ],
    "30000696": [
      "30000693"
    ],
    "30000698": [
      "30000697"
    ],
    "30000699": [
      "30000697",
      "30000700",
      "30000701",
      "30000721"
    ],
    "30000701": [
      "30000697",
      "30000699",
      "30000700"
    ],
    "30000700": [
      "30000699",
      "30000701",
      "30000702",
      "30000722"
    ],
    "30000702": [
      "30000700"
    ],
    "30000703": [
      "30000704",
      "30000705",
      "30000706",
      "30000707",
      "30000978"
    ],
    "30000705": [
      "30000703",
      "30000704",
      "30000707"
    ],
    "30000706": [
      "30000703",
      "30000708",
      "30000787"
    ],
    "30000707": [
      "30000703",
      "30000705",
      "30000708"
    ],
    "30000978": [
      "30000703"
    ],
    "30000708": [
      "30000706",
      "30000707"
    ],
    "30000787": [
      "30000706"
    ],
    "30000709": [
      "30000710",
      "30000711",
      "30000712"
    ],
    "30000711": [
      "30000709",
      "30000712"
    ],
    "30000712": [
      "30000709",
      "30000711",
      "30000713"
    ],
    "30000714": [
      "30000710"
    ],
    "30000713": [
      "30000712",
      "30000789"
    ],
    "30000789": [
      "30000713"
    ],
    "30000715": [
      "30000717",
      "30000718",
      "30000719"
    ],
    "30000718": [
      "30000715",
      "30000716",
      "30000720"
    ],
    "30000719": [
      "30000715",
      "30000720"
    ],
    "30000716": [
      "30000588",
      "30000718"
    ],
    "30000588": [
      "30000716"
    ],
    "30000720": [
      "30000718",
      "30000719",
      "30000774"
    ],
    "30000774": [
      "30000720"
    ],
    "30000725": [
      "30000721",
      "30000726",
      "30000729"
    ],
    "30000729": [
      "30000721",
      "30000725",
      "30000726"
    ],
    "30000723": [
      "30000722"
    ],
    "30000724": [
      "30000722"
    ],
    "30000727": [
      "30000722",
      "30000728"
    ],
    "30000726": [
      "30000725",
      "30000729"
    ],
    "30000728": [
      "30000727"
    ],
    "30000570": [
      "30000730",
      "30000568"
    ],
    "30000731": [
      "30000730"
    ],
    "30000734": [
      "30000730",
      "30000732",
      "30000735"
    ],
    "30000733": [
      "30000732",
      "30000735"
    ],
    "30000735": [
      "30000733",
      "30000734"
    ],
    "30001011": [
      "30001019"
    ],
    "30001016": [
      "30001019",
      "30001018"
    ],
    "30001017": [
      "30001019"
    ],
    "30001018": [
      "30001021",
      "30001016"
    ],
    "30001032": [
      "30001021",
      "30001031"
    ],
    "30001031": [
      "30001029",
      "30001001",
      "30001032",
      "30001033"
    ],
    "30001033": [
      "30001031"
    ]
  }
}